wagtailbettereditor/__init__.py
wagtailbettereditor/wagtail_hooks.py
wagtailbettereditor/static/wagtailbettereditor/css/wagtailbettereditor.css
wagtailbettereditor-1.0.2.dist-info/DESCRIPTION.rst
wagtailbettereditor-1.0.2.dist-info/METADATA
wagtailbettereditor-1.0.2.dist-info/RECORD
wagtailbettereditor-1.0.2.dist-info/WHEEL
wagtailbettereditor-1.0.2.dist-info/metadata.json
wagtailbettereditor-1.0.2.dist-info/top_level.txt
